pubpack.py
pubpack-0.3.dist-info/WHEEL
pubpack-0.3.dist-info/METADATA
pubpack-0.3.dist-info/RECORD
