Metadata-Version: 2.1
Name: pubpack
Version: 0.3
Summary: An amazing sample package!
Home-page: http://nostrame.com
License: UNKNOWN
Author: Frank Nostrame
Author-email: nostrame@gmail.com
Classifier: License :: OSI Approved :: MIT License
